Metadata-Version: 2.1
Name: snarlpy
Version: 0.0.1
Summary: The 'snarlpy' package provides the functionality and a set of examples for the calculation of linkage numbers and optimal cuts of spatially embedded network pairs.
Home-page: https://github.com/felixk1990/network-linkage
Author: felixk1990
Author-email: felixuwekramer@proton.me
License: UNKNOWN
Platform: UNKNOWN
Classifier: Programming Language :: Python :: 3
Classifier: License :: OSI Approved :: MIT License
Classifier: Operating System :: OS Independent
Requires-Python: >=3.8
License-File: LICENSE
